odoo/addons/web_widget_pattern_partner_autocomplete/README.rst
odoo/addons/web_widget_pattern_partner_autocomplete/__init__.py
odoo/addons/web_widget_pattern_partner_autocomplete/__manifest__.py
odoo/addons/web_widget_pattern_partner_autocomplete/demo/res_partner_views.xml
odoo/addons/web_widget_pattern_partner_autocomplete/i18n/it.po
odoo/addons/web_widget_pattern_partner_autocomplete/i18n/web_widget_pattern_partner_autocomplete.pot
odoo/addons/web_widget_pattern_partner_autocomplete/models/__init__.py
odoo/addons/web_widget_pattern_partner_autocomplete/models/base.py
odoo/addons/web_widget_pattern_partner_autocomplete/readme/CONTRIBUTORS.md
odoo/addons/web_widget_pattern_partner_autocomplete/readme/DESCRIPTION.md
odoo/addons/web_widget_pattern_partner_autocomplete/static/description/icon.png
odoo/addons/web_widget_pattern_partner_autocomplete/static/description/index.html
odoo/addons/web_widget_pattern_partner_autocomplete/static/src/autocomplete.xml
odoo_addon_web_widget_pattern_partner_autocomplete-16.0.1.0.0.3.dist-info/METADATA
odoo_addon_web_widget_pattern_partner_autocomplete-16.0.1.0.0.3.dist-info/WHEEL
odoo_addon_web_widget_pattern_partner_autocomplete-16.0.1.0.0.3.dist-info/top_level.txt
odoo_addon_web_widget_pattern_partner_autocomplete-16.0.1.0.0.3.dist-info/RECORD
